rise_set/__init__.py
rise_set/angle.py
rise_set/astrometry.py
rise_set/exceptions.py
rise_set/logging.conf
rise_set/moving_objects.py
rise_set/rates.py
rise_set/sky_coordinates.py
rise_set/transits.py
rise_set/utils.py
rise_set/visibility.py
ocs_rise_set-0.6.4.dist-info/LICENSE
ocs_rise_set-0.6.4.dist-info/METADATA
ocs_rise_set-0.6.4.dist-info/WHEEL
ocs_rise_set-0.6.4.dist-info/RECORD
