Metadata-Version: 2.3
Name: ocs-rise-set
Version: 0.6.4
Summary: Routines for accurate rise/set/transit calculations
Author: Eric Saunders
Author-email: esaunders@lcogt.net
Requires-Python: >=3.9,<3.13
Classifier: License :: OSI Approved :: GNU General Public License v3 (GPLv3)
Classifier: Programming Language :: Python :: 3
Classifier: Programming Language :: Python :: 3.9
Classifier: Programming Language :: Python :: 3.10
Classifier: Programming Language :: Python :: 3.11
Classifier: Programming Language :: Python :: 3.12
Classifier: Topic :: Scientific/Engineering :: Astronomy
Requires-Dist: future (>=0.18.3,<0.19.0)
Requires-Dist: pyslalib (>=1.0.10,<2.0.0)
